{
    "Actor": "鈴奈ひろみ",
    "ActorID": [
        608
    ],
    "ActressesJa": [
        "鈴奈ひろみ"
    ],
    "ActressesEn": [
        "Hiromi Suzuna"
    ],
    "ActressesList": {
        "608": {
            "NameJa": "鈴奈ひろみ",
            "NameEn": "Hiromi Suzuna"
        }
    },
    "AvgRating": 3,
    "CanStream": true,
    "Conditions": null,
    "Desc": "いきなり出だしから「ザーメンが大好き！」と豪語するひろみちゃんは、バスローブで登場です。ハラリと脱いだバスローブの下は、真っ白なセクシー下着！！！\r\n\r\nツンッと立った乳首のある大き目の胸を下から支えただけの何も隠していないブラはセンセーショナルです！とにかくザーメンが好きという要望にお応えして、抜きたくて仕方がない男のズボンをあっさりと下ろし一言、「長いわね〜」。\r\nそして、優しく包み込むように握ってシコシコ動かし始めます。硬くなってきたチ○コをお口に含んで亀頭をレロレロ、そして手も止めずにシコシコ。。。あっという間に口内射精です。\r\nそして、休むまもなくお次の人が下半身を差し出してきます。パンツの上から興味深く撫でなでして、今度は手こきだけで逝かせます。ここで終わるわけも無く、またお次のチ○コがやってきて、手こきとフェラで逝かされます。\r\nたくさんのザーメンに喜ぶひろみちゃん。\r\n\r\n今度は2人の男優さんからおもてなし。オッパイを揉まれ、たっぷり愛撫され、セクシーパンツをずらしておま○こ拝見！そしてクンニ。感じやすいらしく、喘ぎ始めたひろみちゃんのＧスポット攻撃が仕掛けられます。するとチャポチャポっと音がして汁が滴ります。\r\n\r\nお次はひろみちゃんがWフェラでご奉仕。本番は正常位、側位、バックといろんな角度ではめますが、フィニッシュ近くになるとバコッバコッと本当にピストン!!そして顔射!!　ザーメン大好きひろみちゃんもここまですれば大満足だったかな？",
    "Duration": 3854,
    "Expire": null,
    "HasFlash": true,
    "HasGallery": false,
    "HasMemberGalleryZip": false,
    "HasSampleGalleryZip": false,
    "MetaMovieID": 803,
    "MovieID": "033006_853",
    "MovieSeq": 4115,
    "MovieThumb": null,
    "RealMetaMovieID": 805,
    "Release": "2006-03-30",
    "Series": null,
    "SeriesID": null,
    "SiteID": 2470,
    "Status": true,
    "ThumbHigh": "http://www.1pondo.tv/moviepages/033006_853/images/popu.jpg",
    "ThumbLow": "http://www.1pondo.tv/moviepages/033006_853/images/popu.jpg",
    "ThumbMed": "http://www.1pondo.tv/moviepages/033006_853/images/popu.jpg",
    "ThumbUltra": "http://www.1pondo.tv/moviepages/033006_853/images/popu.jpg",
    "Title": "3Pザー汁攻撃!",
    "Type": 0,
    "Year": "2006",
    "UC": [
        39,
        52,
        63,
        69,
        70
    ],
    "UCNAME": [
        "口内発射",
        "美乳",
        "顔射",
        "クンニ",
        "フェラ"
    ],
    "UCNAMEEn": [
        "Cum-in-Mouth",
        "Pretty Tits",
        "Cum-on-Face",
        "Cunnilingus",
        "Blowjob"
    ],
    "UcNameList": {
        "39": {
            "NameEn": "Cum-in-Mouth",
            "NameJa": "口内発射"
        },
        "52": {
            "NameEn": "Pretty Tits",
            "NameJa": "美乳"
        },
        "63": {
            "NameEn": "Cum-on-Face",
            "NameJa": "顔射"
        },
        "69": {
            "NameEn": "Cunnilingus",
            "NameJa": "クンニ"
        },
        "70": {
            "NameEn": "Blowjob",
            "NameJa": "フェラ"
        }
    },
    "IsTicketOnly": false,
    "MemberFiles": [
        {
            "FileName": "240p.mp4",
            "FileSize": 179546320,
            "MetaMovieID": 803,
            "SiteID": "2470",
            "URL": "http://dl11.1pondo.tv/member/movies/033006_853/240p.mp4"
        },
        {
            "FileName": "360p.mp4",
            "FileSize": 227725354,
            "MetaMovieID": 803,
            "SiteID": "2470",
            "URL": "http://dl11.1pondo.tv/member/movies/033006_853/360p.mp4"
        },
        {
            "FileName": "480p.mp4",
            "FileSize": 468697953,
            "MetaMovieID": 803,
            "SiteID": "2470",
            "URL": "http://dl11.1pondo.tv/member/movies/033006_853/480p.mp4"
        }
    ],
    "SampleFiles": [
        {
            "FileName": "240p.mp4",
            "FileSize": 5628078,
            "MetaMovieID": 803,
            "SiteID": "2470",
            "URL": "http://smovie.1pondo.tv/sample/movies/033006_853/240p.mp4"
        },
        {
            "FileName": "360p.mp4",
            "FileSize": 7135589,
            "MetaMovieID": 803,
            "SiteID": "2470",
            "URL": "http://smovie.1pondo.tv/sample/movies/033006_853/360p.mp4"
        },
        {
            "FileName": "480p.mp4",
            "FileSize": 14648823,
            "MetaMovieID": 803,
            "SiteID": "2470",
            "URL": "http://smovie.1pondo.tv/sample/movies/033006_853/480p.mp4"
        }
    ],
    "PPVPrice": {
        "Regular": 0,
        "Discount": 0,
        "Campaign": 0
    }
}